setup.cfg
setup.py
woopra/__init__.py
woopra.egg-info/PKG-INFO
woopra.egg-info/SOURCES.txt
woopra.egg-info/dependency_links.txt
woopra.egg-info/top_level.txt