Metadata-Version: 1.0
Name: woopra
Version: 0.2.2
Summary: Woopra Analytics Tracking API
Home-page: https://github.com/Woopra/woopra-python-sdk
Author: Antoine Chkaiban
Author-email: antoine@woopra.com
License: LICENSE.txt
Platform: UNKNOWN
